pymgl-0.5.0.dist-info/LICENSE
pymgl-0.5.0.dist-info/METADATA
pymgl-0.5.0.dist-info/RECORD
pymgl-0.5.0.dist-info/WHEEL
pymgl-0.5.0.dist-info/top_level.txt
pymgl/_version.py
pymgl/__init__.pyi
pymgl/_pymgl.cpython-310-x86_64-linux-gnu.so
pymgl/__init__.py
pymgl/tests/test_map.py
pymgl/tests/conftest.py
pymgl/tests/test_style.py
pymgl/tests/__init__.py
pymgl/tests/common.py
pymgl/tests/fixtures/mapbox-streets-v11.png
pymgl/tests/fixtures/example-style-geojson.png
pymgl/tests/fixtures/land.mbtiles
pymgl/tests/fixtures/example-style-empty.png
pymgl/tests/fixtures/example-style-remote-image-source.png
pymgl/tests/fixtures/example-style-mbtiles-vector-source@2x.png
pymgl/tests/fixtures/example-style-image-pattern.json
pymgl/tests/fixtures/example-style-geojson-labels.json
pymgl/tests/fixtures/example-style-mbtiles-raster-source.png
pymgl/tests/fixtures/example-style-image-pattern.png
pymgl/tests/fixtures/example-style-geojson-filter.json
pymgl/tests/fixtures/example-pattern.png
pymgl/tests/fixtures/example-style-mapbox-source.json
pymgl/tests/fixtures/example-style-geojson.json
pymgl/tests/fixtures/example-style-geojson-filter.png
pymgl/tests/fixtures/example-style-geojson-hidden-box.json
pymgl/tests/fixtures/test.geojson
pymgl/tests/fixtures/example-style-mbtiles-vector-source.png
pymgl/tests/fixtures/example-style-mbtiles-vector-source.json
pymgl/tests/fixtures/example-style-geojson-features.json
pymgl/tests/fixtures/add-background-layer.png
pymgl/tests/fixtures/example-style-bad-source.json
pymgl/tests/fixtures/geography-class-png.mbtiles
pymgl/tests/fixtures/example-style-remote-raster.png
pymgl/tests/fixtures/example-style-remote-raster.json
pymgl/tests/fixtures/example-style-bad-glyphs.json
pymgl/tests/fixtures/example-style-empty.json
pymgl/tests/fixtures/example-style-bad-source.png
pymgl/tests/fixtures/example-style-bad-remote.json
pymgl/tests/fixtures/example-style-remote-image-source.json
pymgl/tests/fixtures/example-style-geojson-labels.png
pymgl/tests/fixtures/example-style-mapbox-source.png
pymgl/tests/fixtures/add-geojson-point-layer.png
