Metadata-Version: 2.1
Name: pymgl
Version: 0.5.0
Summary: Python wrapper for MapLibre Native
Author-email: "Brendan C. Ward" <bcward@astutespruce.com>
License: MIT License
Project-URL: Home, https://github.com/brendan-ward/pymgl
Project-URL: Repository, https://github.com/brendan-ward/pymgl
Classifier: Development Status :: 4 - Beta
Classifier: Intended Audience :: Science/Research
Classifier: License :: OSI Approved :: MIT License
Classifier: Operating System :: OS Independent
Classifier: Programming Language :: Python :: 3
Classifier: Topic :: Scientific/Engineering :: GIS
Requires-Python: >=3.9
License-File: LICENSE
Requires-Dist: packaging
Provides-Extra: bench
Requires-Dist: numpy ; extra == 'bench'
Requires-Dist: Pillow ; extra == 'bench'
Requires-Dist: pixelmatch ; extra == 'bench'
Requires-Dist: python-dotenv ; extra == 'bench'
Requires-Dist: pytest ; extra == 'bench'
Requires-Dist: pytest-benchmark ; extra == 'bench'
Requires-Dist: requests ; extra == 'bench'
Provides-Extra: dev
Requires-Dist: numpy ; extra == 'dev'
Requires-Dist: Pillow ; extra == 'dev'
Requires-Dist: pre-commit ; extra == 'dev'
Requires-Dist: ruff ; extra == 'dev'
Requires-Dist: setuptools ; extra == 'dev'
Requires-Dist: versioneer ; extra == 'dev'
Provides-Extra: slownetwork
Requires-Dist: poorconn ; extra == 'slownetwork'
Provides-Extra: test
Requires-Dist: numpy ; extra == 'test'
Requires-Dist: Pillow ; extra == 'test'
Requires-Dist: pixelmatch ; extra == 'test'
Requires-Dist: python-dotenv ; extra == 'test'
Requires-Dist: pytest ; extra == 'test'
Requires-Dist: pytest-cov ; extra == 'test'
